magent-0.2.4.dist-info/top_level.txt
magent-0.2.4.dist-info/WHEEL
magent-0.2.4.dist-info/METADATA
magent-0.2.4.dist-info/RECORD
magent-0.2.4.dist-info/LICENSE
magent/c_lib.py
magent/libmagent.so
magent/environment.py
magent/testlib
magent/utility.py
magent/gridworld.py
magent/render.py
magent/__init__.py
magent/builtin/__init__.py
magent/builtin/config/battle.py
magent/builtin/config/double_attack.py
magent/builtin/config/forest.py
magent/builtin/config/pursuit.py
magent/builtin/config/__init__.py
