Metadata-Version: 2.1
Name: magent
Version: 0.2.4
Summary: Multi-Agent Reinforcement Learning environments with very large numbers of agents
Home-page: https://github.com/Farama-Foundation/MAgent
Author: Farama Foundation
Author-email: jkterry@farama.org
License: UNKNOWN
Keywords: Reinforcement Learning,game,RL,AI
Platform: UNKNOWN
Classifier: Development Status :: 5 - Production/Stable
Classifier: Programming Language :: Python :: 3
Classifier: Programming Language :: Python :: 3.7
Classifier: Programming Language :: Python :: 3.8
Classifier: Programming Language :: Python :: 3.9
Classifier: Programming Language :: Python :: 3.10
Classifier: License :: OSI Approved :: MIT License
Classifier: Operating System :: OS Independent
Requires-Python: >=3.7
